[{"property_type":"단독다가구","trade_type":"전월세","region_name":"강남구","month":"2026-04","count":9,"avg_price":14111.0},{"property_type":"단독다가구","trade_type":"전월세","region_name":"서대문구","month":"2026-04","count":6,"avg_price":5417.0},{"property_type":"단독다가구","trade_type":"전월세","region_name":"용산구","month":"2026-04","count":2,"avg_price":825.0},{"property_type":"아파트","trade_type":"매매","region_name":"강남구","month":"2026-04","count":12,"avg_price":180392.0},{"property_type":"아파트","trade_type":"매매","region_name":"서대문구","month":"2026-04","count":3,"avg_price":94667.0},{"property_type":"아파트","trade_type":"전월세","region_name":"강남구","month":"2026-04","count":226,"avg_price":65976.0},{"property_type":"아파트","trade_type":"전월세","region_name":"서대문구","month":"2026-04","count":1,"avg_price":55650.0},{"property_type":"아파트","trade_type":"전월세","region_name":"용산구","month":"2026-04","count":2,"avg_price":89500.0},{"property_type":"연립다세대","trade_type":"매매","region_name":"강남구","month":"2026-04","count":10,"avg_price":63450.0},{"property_type":"연립다세대","trade_type":"매매","region_name":"서대문구","month":"2026-04","count":1,"avg_price":62000.0},{"property_type":"연립다세대","trade_type":"전월세","region_name":"강남구","month":"2026-04","count":106,"avg_price":25564.0},{"property_type":"연립다세대","trade_type":"전월세","region_name":"서대문구","month":"2026-04","count":8,"avg_price":21524.0},{"property_type":"연립다세대","trade_type":"전월세","region_name":"용산구","month":"2026-04","count":3,"avg_price":13000.0},{"property_type":"오피스텔","trade_type":"매매","region_name":"강남구","month":"2026-04","count":20,"avg_price":36730.0},{"property_type":"오피스텔","trade_type":"매매","region_name":"서대문구","month":"2026-04","count":1,"avg_price":9500.0},{"property_type":"오피스텔","trade_type":"전월세","region_name":"강남구","month":"2026-04","count":62,"avg_price":13116.0},{"property_type":"오피스텔","trade_type":"전월세","region_name":"서대문구","month":"2026-04","count":1,"avg_price":500.0},{"property_type":"단독다가구","trade_type":"매매","region_name":"강남구","month":"2026-03","count":4,"avg_price":583000.0},{"property_type":"단독다가구","trade_type":"매매","region_name":"서대문구","month":"2026-03","count":4,"avg_price":208625.0},{"property_type":"단독다가구","trade_type":"매매","region_name":"용산구","month":"2026-03","count":1,"avg_price":417500.0},{"property_type":"단독다가구","trade_type":"전월세","region_name":"강남구","month":"2026-03","count":31,"avg_price":10122.0},{"property_type":"단독다가구","trade_type":"전월세","region_name":"서대문구","month":"2026-03","count":26,"avg_price":2346.0},{"property_type":"단독다가구","trade_type":"전월세","region_name":"용산구","month":"2026-03","count":11,"avg_price":9909.0},{"property_type":"아파트","trade_type":"매매","region_name":"강남구","month":"2026-03","count":119,"avg_price":217350.0},{"property_type":"아파트","trade_type":"매매","region_name":"서대문구","month":"2026-03","count":17,"avg_price":94076.0},{"property_type":"아파트","trade_type":"매매","region_name":"용산구","month":"2026-03","count":8,"avg_price":301525.0},{"property_type":"아파트","trade_type":"전월세","region_name":"강남구","month":"2026-03","count":1352,"avg_price":60676.0},{"property_type":"아파트","trade_type":"전월세","region_name":"서대문구","month":"2026-03","count":15,"avg_price":39980.0},{"property_type":"아파트","trade_type":"전월세","region_name":"용산구","month":"2026-03","count":30,"avg_price":47017.0},{"property_type":"연립다세대","trade_type":"매매","region_name":"강남구","month":"2026-03","count":51,"avg_price":70406.0},{"property_type":"연립다세대","trade_type":"매매","region_name":"서대문구","month":"2026-03","count":8,"avg_price":38875.0},{"property_type":"연립다세대","trade_type":"매매","region_name":"용산구","month":"2026-03","count":1,"avg_price":270000.0},{"property_type":"연립다세대","trade_type":"전월세","region_name":"강남구","month":"2026-03","count":612,"avg_price":19838.0},{"property_type":"연립다세대","trade_type":"전월세","region_name":"서대문구","month":"2026-03","count":46,"avg_price":10893.0},{"property_type":"연립다세대","trade_type":"전월세","region_name":"용산구","month":"2026-03","count":11,"avg_price":43045.0},{"property_type":"오피스텔","trade_type":"매매","region_name":"강남구","month":"2026-03","count":88,"avg_price":30073.0},{"property_type":"오피스텔","trade_type":"매매","region_name":"서대문구","month":"2026-03","count":8,"avg_price":11775.0},{"property_type":"오피스텔","trade_type":"매매","region_name":"용산구","month":"2026-03","count":1,"avg_price":78200.0},{"property_type":"오피스텔","trade_type":"전월세","region_name":"강남구","month":"2026-03","count":337,"avg_price":12228.0},{"property_type":"오피스텔","trade_type":"전월세","region_name":"서대문구","month":"2026-03","count":20,"avg_price":3525.0},{"property_type":"오피스텔","trade_type":"전월세","region_name":"용산구","month":"2026-03","count":1,"avg_price":160000.0}]